mcp_server_hacker_news/__init__.py
mcp_server_hacker_news/__main__.py
mcp_server_hacker_news/server.py
mcp_server_hacker_news-0.1.4.dist-info/METADATA
mcp_server_hacker_news-0.1.4.dist-info/WHEEL
mcp_server_hacker_news-0.1.4.dist-info/entry_points.txt
mcp_server_hacker_news-0.1.4.dist-info/RECORD
